software_manager/__init__.py
software_manager/choices.py
software_manager/custom_exceptions.py
software_manager/filters.py
software_manager/forms.py
software_manager/logger.py
software_manager/models.py
software_manager/navigation.py
software_manager/tables.py
software_manager/upgrade.py
software_manager/urls.py
software_manager/views.py
software_manager/worker.py
software_manager/migrations/0001_initial.py
software_manager/migrations/0002_scheduledtask_transfer_method.py
software_manager/migrations/__init__.py
software_manager/templates/software_manager/golden_image_list.html
software_manager/templates/software_manager/my_obj_list.html
software_manager/templates/software_manager/my_render_field.html
software_manager/templates/software_manager/scheduledtask_add.html
software_manager/templates/software_manager/scheduledtask_info.html
software_manager/templates/software_manager/scheduledtask_list.html
software_manager/templates/software_manager/software_list.html
software_manager/templates/software_manager/upgrade_device_list.html
software_manager/templatetags/__init__.py
software_manager/templatetags/my_form_helpers.py
netbox_plugin_software_manager-0.0.3.dist-info/LICENSE
netbox_plugin_software_manager-0.0.3.dist-info/METADATA
netbox_plugin_software_manager-0.0.3.dist-info/WHEEL
netbox_plugin_software_manager-0.0.3.dist-info/top_level.txt
netbox_plugin_software_manager-0.0.3.dist-info/RECORD
