Metadata-Version: 2.1
Name: netbox-plugin-software-manager
Version: 0.0.3
Summary: Software Manager for Cisco IOS/IOS-XE devices
Home-page: https://github.com/alsigna/netbox-software-manager
Author: Alexander Ignatov
License: MIT
Platform: UNKNOWN
Requires-Dist: scrapli[paramiko]
Requires-Dist: rq-scheduler
Requires-Dist: xlsxwriter
